artellalauncher/__init__.py
artellalauncher/__version__.py
artellalauncher/launcher.json
artellalauncher/updater.json
artellalauncher/artelladccs/__init__.py
artellalauncher/artelladccs/houdinidcc.py
artellalauncher/artelladccs/mayadcc.py
artellalauncher/artelladccs/nukedcc.py
artellalauncher/artelladccs/photoshopdcc.py
artellalauncher/artelladccs/substancedesignerdcc.py
artellalauncher/artelladccs/substancepainterdcc.py
artellalauncher/artelladccs/zbrushdcc.py
artellalauncher/core/__init__.py
artellalauncher/core/config.py
artellalauncher/core/dccselector.py
artellalauncher/core/defines.py
artellalauncher/core/launcher.py
artellalauncher/core/updater.py
artellalauncher/resources/icons/color/artella.png
artellalauncher/resources/icons/color/console.png
artellalauncher/resources/icons/color/houdini.png
artellalauncher/resources/icons/color/maya.png
artellalauncher/resources/icons/color/nuke.png
artellalauncher/resources/icons/color/photoshop.png
artellalauncher/resources/icons/color/search_folder.png
artellalauncher/resources/icons/color/substance_designer.png
artellalauncher/resources/icons/color/substance_painter.png
artellalauncher/resources/icons/color/uninstall.png
artellalauncher/resources/icons/color/zbrush.png
artellalauncher/resources/images/splash.png
artellalauncher/utils/__init__.py
artellalauncher/utils/download.py
artellalauncher/widgets/__init__.py
artellalauncher/widgets/console.py
artellalauncher-0.0.8.dist-info/LICENSE
artellalauncher-0.0.8.dist-info/METADATA
artellalauncher-0.0.8.dist-info/WHEEL
artellalauncher-0.0.8.dist-info/top_level.txt
artellalauncher-0.0.8.dist-info/RECORD
