Metadata-Version: 2.1
Name: artellalauncher
Version: 0.0.8
Summary: Artella Launcher can be used to create Artella based project launchers
Home-page: UNKNOWN
Author: Tomas Poveda
Author-email: tpovedatd@gmail.com
License: MIT
Platform: UNKNOWN
Requires-Dist: artellapipe
Requires-Dist: pathlib2
Requires-Dist: requests
Requires-Dist: packaging
Requires-Dist: beautifulsoup4
Requires-Dist: lxml
Provides-Extra: dev
Requires-Dist: wheel ; extra == 'dev'
Provides-Extra: test
Requires-Dist: pytest ; extra == 'test'
